[
  {
    "id": "624b5fdd7f524f73d062daef",
    "picture": "./images/man2.jpg",
    "name": "Cain Fitzpatrick",
    "comment": "Trusted Prodcuts with much better verification and authintication. Love them for their honesty soo much!!!",
    "ratings": "4.5"
  },
  {
    "id": "624b5fdd51851168d4b6916c",
    "picture": "./images/man8.jpg",
    "name": "Norma Atkinson",
    "comment": "One of the best Jersey Selling pages i have come acrossed,Kudos to them! Best designs with awesome customer support from them",
    "ratings": "4"
  },
  {
    "id": "624b5fdd80604a3985b0f26e",
    "picture": "./images/man9.jpg",
    "name": "Casandra Dyer",
    "comment": "I just love their products and everything. They are the best in terms of selling Jerseys and i get the new design whenever i want. Please buy from them!",
    "ratings": "4.5"
  },
  {
    "id": "624b5fdd4129cc2f18096c61",
    "picture": "./images/man1.jpg",
    "name": "Mckinney Greene",
    "comment": "Trusted Prodcuts with much better verification and authintication. Love them for their honesty soo much. Quality over everything for them.",
    "ratings": "4"
  },
  {
    "id": "624b5fdd3a44f3b05d1776cb",
    "picture": "./images/man3.jpg",
    "name": "Fleming Savage",
    "comment": "One of the best Jersey Selling pages i have come acrossed,Kudos to them! Best designs with awesome customer support from them.",
    "ratings": "5"
  },
  {
    "id": "624b5fddfd9cca6151971e7f",
    "picture": "./images/man4.jpg",
    "name": "Welch Murray",
    "comment": "they are doing absolutely great in jersey sellings. please buy from them!\r\n",
    "ratings": "4"
  },
  {
    "id": "624b5fdd951f1e8ac28bad5c",
    "picture": "./images/man5.jpg",
    "name": "Potts Wells",
    "comment": " I just love their products and everything. They are the best in terms of selling Jerseys and i get the new design whenever i want. Please buy from them!",
    "ratings": "4.5"
  },
  {
    "id": "624b5fddf0aee71292e3338a",
    "picture": "./images/man6.jpg",
    "name": "Minnie French",
    "comment": "they are doing absolutely great in jersey sellings. please buy from them!",
    "ratings": "4"
  },
  {
    "id": "624b5fdd1ea7e55fcc2e71d7",
    "picture": "./images/man7.jpg",
    "name": "Hartman Aguilar",
    "comment": "I just love their products and everything. They are the best in terms of selling Jerseys and i get the new design whenever i want. Please buy from them!",
    "ratings": "4.5"
  }
]